dokky.py
dokky-0.1.0.dist-info/DESCRIPTION.rst
dokky-0.1.0.dist-info/METADATA
dokky-0.1.0.dist-info/RECORD
dokky-0.1.0.dist-info/WHEEL
dokky-0.1.0.dist-info/metadata.json
dokky-0.1.0.dist-info/top_level.txt
