Metadata-Version: 2.0
Name: dokky
Version: 0.1.0
Summary: Python client for Docsbox
Home-page: https://github.com/docsbox/dokky
Author: Dmitry Veselov
Author-email: d.a.veselov@yandex.ru
License: MIT
Platform: UNKNOWN
Classifier: Intended Audience :: Developers
Classifier: Programming Language :: Python :: 2
Classifier: Programming Language :: Python :: 3
Classifier: Programming Language :: Python :: Implementation :: CPython
Classifier: Programming Language :: Python :: Implementation :: PyPy
Requires-Dist: requests (==2.10.0)
